savantaudio/__init__.py
savantaudio/__version__.py
savantaudio/client.py
savantaudio/entry_points.py
savantaudio_client-1.0.1.dist-info/licenses/LICENSE
savantaudio_client-1.0.1.dist-info/METADATA
savantaudio_client-1.0.1.dist-info/WHEEL
savantaudio_client-1.0.1.dist-info/entry_points.txt
savantaudio_client-1.0.1.dist-info/top_level.txt
savantaudio_client-1.0.1.dist-info/RECORD
