Metadata-Version: 2.4
Name: savantaudio-client
Version: 1.0.1
Summary: A client library to interact with Savant Audio Switches (e.g. SSA-3220).
Home-page: https://github.com/adam_kropp/savantaudio-client
Author: Adam Kropp
Author-email: adam_kropp@yahoo.com
Classifier: Programming Language :: Python :: 3.11
Classifier: License :: OSI Approved :: MIT License
Classifier: Operating System :: OS Independent
Classifier: Development Status :: 4 - Beta
Classifier: Intended Audience :: Developers
Requires-Python: >=3.11
License-File: LICENSE
Dynamic: license-file
